infoweb/__init__.py
infoweb/infoweb.py
infoweb-1.4.dist-info/METADATA
infoweb-1.4.dist-info/WHEEL
infoweb-1.4.dist-info/top_level.txt
infoweb-1.4.dist-info/RECORD
